<annotation>
	<folder>helico_images</folder>
	<filename>ID4630_Mi2_SP_SN-06XP_1.jpg</filename>
	<path>/root/Bureau/data_science/helico_images/ID4630_Mi2_SP_SN-06XP_1.jpg</path>
	<source>
		<database>Unknown</database>
	</source>
	<size>
		<width>1024</width>
		<height>708</height>
		<depth>3</depth>
	</size>
	<segmented>0</segmented>
	<object>
		<name>number</name>
		<pose>Unspecified</pose>
		<truncated>0</truncated>
		<difficult>0</difficult>
		<bndbox>
			<xmin>730</xmin>
			<ymin>429</ymin>
			<xmax>847</xmax>
			<ymax>485</ymax>
		</bndbox>
	</object>
	<object>
		<name>number</name>
		<pose>Unspecified</pose>
		<truncated>1</truncated>
		<difficult>0</difficult>
		<bndbox>
			<xmin>981</xmin>
			<ymin>324</ymin>
			<xmax>1024</xmax>
			<ymax>366</ymax>
		</bndbox>
	</object>
	<object>
		<name>number</name>
		<pose>Unspecified</pose>
		<truncated>0</truncated>
		<difficult>0</difficult>
		<bndbox>
			<xmin>279</xmin>
			<ymin>376</ymin>
			<xmax>336</xmax>
			<ymax>393</ymax>
		</bndbox>
	</object>
</annotation>
