<annotation>
	<folder>helico_jetson_photo</folder>
	<filename>ID_8668128_59150_1501409946.jpg</filename>
	<path>/root/Bureau/data_science/helico_jetson_photo/ID_8668128_59150_1501409946.jpg</path>
	<source>
		<database>Unknown</database>
	</source>
	<size>
		<width>1920</width>
		<height>1099</height>
		<depth>3</depth>
	</size>
	<segmented>0</segmented>
	<object>
		<name>number</name>
		<pose>Unspecified</pose>
		<truncated>0</truncated>
		<difficult>0</difficult>
		<bndbox>
			<xmin>773</xmin>
			<ymin>765</ymin>
			<xmax>912</xmax>
			<ymax>826</ymax>
		</bndbox>
	</object>
</annotation>
